Workbook

Sheet ReadMe
A1: NORCO — Group Investor Model
A2: Vestwoods (Haier Energy) + Al Reem Plastics (Angola) | Investment into NORCO Egypt | Aug 2026 – Jul 2031
A4: Purpose | B4: Investor-grade 5-year model for NORCO's two-division distribution platform. The investor invests USD 1,500,000 into the EGYPT operating company for 50% of its shares.
A5: Divisions & markets | B5: Vestwoods lithium BESS: Egypt, Sudan, Algeria, Libya. Al Reem Plastics houseware (sourced from the group's Angola plant): Egypt and Sudan from Year 1, Nigeria from Year 2.
A6: Vestwoods economics | B6: 40ft container of 340 units. COGS = 72% of revenue at retail, 87% at wholesale (verified pricing list). Egypt sells 50% retail / 50% wholesale; all export markets wholesale-only.
A7: Al Reem economics | B7: 40ft container of 20,488 units / 69 SKUs (July-2026 packing list), landed cost USD 59,343. NORCO buys 30% below price list: margin = 30% of retail revenue, 20% of wholesale revenue. Egypt 50/50 retail-wholesale; Sudan wholesale-only.
A8: Container plan | B8: Vestwoods — Egypt 6/7/9/11/15, Sudan 4/5/6/8/10, Algeria 3/4/6/7/8, Libya 0/4/5/6/8. Al Reem — Egypt 10/12/15/18/20, Sudan 5/8/10/12/15 (Y1..Y5).
A9: Investment ask | B9: USD 1,000,000 core for 50% of NORCO Egypt — Tranche 1 USD 500K at close (Aug-26), Tranche 2 USD 500K at Month 4 (milestone-gated) — plus an optional USD 500K accelerator (ceiling USD 1.5M).
A10: Shareholding | B10: NORCO Egypt: Investor 50% | NORCO UAE 20% | Founder 20% | Partner A 5% | Partner B 5%. Founder-side combined interest 40% (20% direct + 20% via NORCO UAE).
A11: Currency & FX | B11: USD throughout. Planning rate USD 1 = EGP 53. Corporate tax 22.5% on net profit; Year-1 tax computed with loss carry-forward.
A12: Supplier terms | B12: Vestwoods Year 1: 100% payment before shipment; from Month 13: 10% down + 90% at 3-month credit. Al Reem (affiliate): paid against shipping documents.
A13: Sheets | B13: Key Assumptions | Pre-Op Investment | Pricing Reference | Staff Plan | Monthly P&L Year 1 | Annual P&L Summary Y1-Y5 | Cash Flow Year 1 | 5Y Cash Flow | Market Detail | Funding & Returns | Shareholding | Dashboard
A14: Version | B14: V5 (Group) — 14 July 2026. Strictly Private & Confidential. Prepared by Fadi Jannan, Managing Director.

Sheet Key Assumptions
A1: Key Assumptions & Financial Model Notes
A3: Parameter | B3: Value / Assumption | C3: Notes
A4: ► GENERAL
A5: Business start | B5: August 2026 | C5: Month 1 = Aug-26; fiscal years run Aug–Jul
A6: Scope | B6: Two divisions on one platform | C6: Vestwoods (Haier Energy) BESS + Al Reem Plastics houseware
A7: Investment vehicle | B7: USD 1,000,000 core for 50% of NORCO Egypt | C7: T1 500K + T2 500K; optional 500K accelerator (ceiling 1.5M)
A8: FX planning rate | B8: USD 1 = EGP 53 | C8: Conservative vs spot ~49–51
A9: Corporate tax | B9: 22.5% on net profit | C9: Loss carry-forward applied in Year 1
A10: ► VESTWOODS
A11: Markets
A12: Container | B12: 340 units / 40ft, COGS USD 342,316 | C12: Supplier prepay USD 239,805 + local import costs USD 102,511
A13: COGS — retail | B13: 72% of revenue | C13: Container retail value USD 472,680
A14: COGS — wholesale | B14: 87% of revenue | C14: Container wholesale value USD 393,882
A15: Egypt mix | B15: 50% retail / 50% wholesale | C15: Blended Egypt revenue USD 433,281/container (21.0% GM)
A16: Container plan Y1→Y5
A17: Supplier terms Y1 | B17: 100% payment before shipment | C17: Drives the working-capital need and the raise
A18: Supplier terms Y2+ | B18: 10% down + 90% at 3-month credit | C18: From Month 13 — releases ~90% of container capital
A19: ► AL REEM PLASTICS (ANGOLA)
A20: Markets | B20: Egypt and Sudan | C20: Export corridors expand later
A21: Sourcing | B21: Affiliated plant in Angola — 30% below price list | C21: Margin ≈ 25% of Egypt revenue (blended retail/wholesale, COGS 75%); 17.4% on export wholesale (COGS 82.64%)
A22: Container | B22: 20,488 units / 69 SKUs, COGS USD 43,339 | C22: Priced line-by-line from the July-2026 Egypt packing list
A23: Egypt revenue / container | B23: USD 57,688 (50/50 retail-wholesale) | C23: GM 25.3% blended
A24: Sudan revenue / container | B24: USD 52,444 (wholesale) | C24: GM 20.0%; 50% advance + 50% on delivery
A25: Container plan Y1→Y5 | B25: Egypt 10→40 | Sudan 5→30 | Nigeria 0→25 | C25: 95 containers by Year 5
A26: Supplier terms | B26: 100% credit
A27: ► CUSTOMER TERMS
A28: Egypt customers | B28: 30–60 days (avg 45); 1-month collection lag | C28: Invoice on delivery
A29: Sudan | B29: 50% advance at order + 50% on delivery | C29: Cash before/at shipment
A30: Algeria | B30: 100% LC before shipment (FOB Jebel Ali) | C30: Licensed importer; zero in-country exposure
A31: Libya | B31: Advance / confirmed LC | C31: From Year 2, dual-hub distributors
A32: ► FACILITIES & STAFF
A33: Showroom #1 | B33: 6th October City — OPERATIONAL | C33: EGP 10,000/mo = USD 200; renovated & furnished
A34: Showroom #2 | B34: New Cairo ~100 sqm — opens Month 1 | C34: USD 2,500/month (as modelled in the P&L)
A35: Office | B35: New Cairo, ~100 sqm furnished | C35: USD 3,000/month
A36: Warehouse | B36: 300–700 sqm — 6th Oct / Sheikh Zayed / New Cairo | C36: USD 3,000/month; located on best available cost
A37: Sales compensation | B37: Salary + 4% (Vestwoods) / 3% (Al Reem) commission on Egypt sales | C37: Commission on both divisions' Egypt revenue
A38: Headcount | B38: 19 (M12) → 55 (Year 5) | C38: Full roster in Staff Plan sheet
A39: ► ADDITIONAL SETUP COSTS (YEAR 1)
A40: Office Furniture & IT | B40: USD 40,000 (capitalized) | C40: Desks, computers, server, phones
A41: Warehouse Shelving & Equipment | B41: USD 10,400 (capitalized) | C41: Racking, forklifts, safety equipment
A42: Security Deposits (3 months) | B42: USD 14,667 | C42: Showroom USD 567 + office USD 6,600 + warehouse USD 7,500 — refundable
A43: GOEI Import Registration | B43: USD 3,000 (expensed Month 1–3) | C43: Required for product import compliance
A44: Demo / Showroom Units | B44: USD 5,000 (expensed Month 1) | C44: Operational display inventory
A45: Annual Amortisation on Setup | B45: USD 16,800/year (USD 1,400/month) | C45: 50K fit-out / 3 years
A46: ► FUNDING
A47: Investment | B47: USD 1,500,000 for 50% of NORCO Egypt | C47: Band USD 1.0M – 1.5M; two tranches
A48: Peak funding need | B48: USD 903,954 (self-funded deficit, Jan-27) | C48: Covered by the 1.0M raise; minimum cash +USD 96,046
A49: Dividend policy | B49: 100% of net profit distributed, in arrears | C49: Investor receives 50% of each distribution

Sheet Pre-Op Investment
A1: Pre-Operational Investment (Already Spent by Founder)
A2: Incurred before the August 2026 launch — demonstrates founder commitment and operational readiness
A3: Description | B3: Date | C3: Original Amount | D3: USD | E3: Category
A4: Showroom renovation — 6th October City | B4: Jun 2026 | C4: EGP 82,000 | D4: 1640 | E4: Capex — Fit-out
A5: Showroom furniture & fittings | B5: Jun 2026 | C5: EGP 85,000 | D5: 1700 | E5: Capex — Fit-out
A6: Security cameras & CCTV | B6: Jun 2026 | C6: EGP 7,500 | D6: 150 | E6: Capex — Security
A7: Additional setup & equipment | B7: Jun 2026 | C7: EGP 50,000 | D7: 1000 | E7: Capex — Equipment
A8: Legal & licensing — Egypt company registration | B8: Jul 2025 | C8: EGP 87,000 | D8: 1740 | E8: OpEx — Legal/Egypt
A9: Legal & licensing — import permits Egypt | B9: Jun 2026 | C9: EGP 80,000 | D9: 1600 | E9: OpEx — Legal/Egypt
A10: UAE business licence — NORCO General Trading LLC | B10: 2025–2026 | C10: AED 15,000 | D10: 4084 | E10: OpEx — Legal/UAE
A11: Showroom rent — pre-operations (2 months) | B11: Jun–Jul 2026 | C11: EGP 20,000 | D11: 400 | E11: OpEx — Rent
A12: Sales representative salary — 2 months pre-launch | B12: Jun–Jul 2026 | C12: 2 × USD 500 | D12: 1000 | E12: OpEx — Salaries
A13: Products purchased & sold through showroom (pre-launch trading) | B13: Jun–Jul 2026 | C13: EGP 31,948.50 | D13: 603 | E13: Working capital — Inventory
A14: Company branding, logo & stationery | B14: 2025 | C14: USD 300 | D14: 300 | E14: OpEx — Marketing
A15: Corporate website — norcotrading.com | B15: 2025 | C15: USD 300 | D15: 300 | E15: OpEx — Marketing
A16: TOTAL PRE-OPERATIONAL INVESTMENT | D16: =SUM(D4:D15)

Sheet Pricing Reference
A1: Pricing Reference — Both Divisions
A2: A. VESTWOODS — verified unit pricing (USD)
A3: EGP 53 = USD 1 | 40ft container USD 6,865 shipping | landed = factory + freight + 5% duty + 2% GOEI + handling
A4: Category | B4: Model | C4: Description | D4: Factory | E4: COGS | F4: Wholesale | G4: Retail USD | H4: Retail EGP
A5: RESIDENTIAL | B5: VE51100L | C5: Smart Battery 5.12kWh L-Series IP21 | D5: 672 | E5: 988 | F5: 1137 | G5: 1364 | H5: =G5*53 | I5: =(G5-E5)/E5
A6: RESIDENTIAL | B6: VE51200L | C6: Smart Battery 10.24kWh L-Series IP21 | D6: 1200 | E6: 1748 | F6: 2011 | G6: 2413 | H6: =G6*53 | I6: =(G6-E6)/E6
A7: RESIDENTIAL | B7: VE51314L | C7: Smart Battery 16.07kWh L-Series IP21 | D7: 1560 | E7: 2266 | F7: 2607 | G7: 3129 | H7: =G7*53 | I7: =(G7-E7)/E7
A8: RESIDENTIAL | B8: HEH-S6KB3-LV | C8: Hybrid Inverter 6kW IP65 | D8: 390 | E8: 582 | F8: 670 | G8: 804 | H8: =G8*53 | I8: =(G8-E8)/E8
A9: RESIDENTIAL | B9: VEH-T20KA3-LV | C9: 3-Phase Inverter 20kW | D9: 1870 | E9: 2713 | F9: 3121 | G9: 3745 | H9: =G9*53 | I9: =(G9-E9)/E9
A10: RESIDENTIAL | B10: VEP1K20 | C10: Rescube All-in-One 1kW/2kWh | D10: 365 | E10: 546 | F10: 628 | G10: 754 | H10: =G10*53 | I10: =(G10-E10)/E10
A11: RESIDENTIAL | B11: VEP500W | C11: Rescube Portable 500W/1kWh | D11: 145 | E11: 229 | F11: 264 | G11: 317 | H11: =G11*53 | I11: =(G11-E11)/E11
A12: C&I | B12: VCCU200-F05-SE | C12: HV Control Box 20kWh BMS | D12: 1400 | E12: 2044 | F12: 2361 | G12: 2833 | H12: =G12*53 | I12: =(G12-E12)/E12
A13: C&I | B13: VEC64314SE | C13: C&I Battery Module 20kWh | D13: 160 | E13: 258 | F13: 308 | G13: 369 | H13: =G13*53 | I13: =(G13-E13)/E13
A14: C&I | B14: VEB 704-221kWh | C14: Industrial Cabinet 221kWh | D14: 27300 | E14: 39340 | F14: 45251 | G14: 54302 | H14: =G14*53 | I14: =(G14-E14)/E14
A15: C&I | B15: VEB 832-261kWh | C15: Industrial Cabinet 261kWh | D15: 31350 | E15: 45172 | F15: 51958 | G15: 62350 | H15: =G15*53 | I15: =(G15-E15)/E15
A16: C&I | B16: S6-EH3P50K-H | C16: Commercial Inverter 50kW | D16: 3995 | E16: 5781 | F16: 6658 | G16: 7990 | H16: =G16*53 | I16: =(G16-E16)/E16
... A18: TELECOM | B18: VT48100E | C18: Telecom Battery 48V/100Ah | D18: 563 | E18: 835 | F18: 1044 | G18: 1253 | H18: =G18*53 | I18: =(G18-E18)/E18
A19: TELECOM | C19: Smart features: GPS, Bluetooth | D19: 104 | E19: 182 | F19: 206 | G19: 247 | H19: =G19*53 | I19: =(G19-E19)/E19
A20: TELECOM | B20: IMDC 36KW | C20: Integrated Power System 36kW | D20: 2426 | E20: 3518 | F20: 4403 | G20: 5284 | H20: =G20*53 | I20: =(G20-E20)/E20
A21: TELECOM | C21: Outdoor cabinet-1 | D21: 2739 | E21: 3968 | F21: 4787 | G21: 5744 | H21: =G21*53 | I21: =(G21-E21)/E21
A22: TELECOM | C22: Outdoor cabinet-2 | D22: 2555 | E22: 3704 | F22: 4268 | G22: 5122 | H22: =G22*53 | I22: =(G22-E22)/E22
A23: TELECOM | B23: ZHS484KG-2 | C23: Rectifier | D23: 173 | E23: 273 | F23: 342 | G23: 410 | H23: =G23*53 | I23: =(G23-E23)/E23
A24: TELECOM | B24: ZHS483KG | C24: Solar | D24: 180 | E24: 284 | F24: 355 | G24: 426 | H24: =G24*53 | I24: =(G24-E24)/E24
A25: B. AL REEM PLASTICS — container economics (Angola, affiliated supply)
A26: EGP 53 = USD 1 | 40ft container USD 2,500 shipping | landed = factory + freight + 5% duty + 2% GOEI + handling
A27: Model | C27: Code | D27: Factory | E27: COGS | F27: Wholesale | G27: Retail USD
A28: Sima Closet | C28: 2601 | D28: 30.22 | E28: 36.9865 | F28: 42.712499 | G28: 51.254998 | I28: =(G28-E28)/E28
A29: Sima Double closet | C29: 2681 | D29: 50.05 | E29: 61.14 | F29: 70.489024 | G29: 84.586828 | I29: =(G29-E29)/E29
A30: Sugar box with cover and spoon | C30: 1200 | D30: 0.308 | E30: 0.5452 | F30: 0.80500363 | G30: 0.96600435 | I30: =(G30-E30)/E30
A31: Round bowl 15cm | C31: 601 | D31: 0.1155 | E31: 0.3107 | F31: 0.53532863 | G31: 0.64239435 | I31: =(G31-E31)/E31
A32: Round bowl 18cm | C32: 602 | D32: 0.1386 | E32: 0.33884 | F32: 0.56768963 | G32: 0.68122755 | I32: =(G32-E32)/E32
A33: Round bowl 32cm | C33: 8 | D33: 0.6391 | E33: 0.94854 | F33: 1.2688446 | G33: 1.5226136 | I33: =(G33-E33)/E33
A34: Round bowl 36cm | C34: 607 | D34: 0.924 | E34: 1.2956 | F34: 1.6679636 | G34: 2.0015564 | I34: =(G34-E34)/E34
A35: Round bowl 45cm | C35: 608 | D35: 1.54 | E35: 2.046 | F35: 2.5309236 | G35: 3.0371084 | I35: =(G35-E35)/E35
A36: Round bowl 55cm | C36: 610 | D36: 2.002 | E36: 2.6088 | F36: 3.1781436 | G36: 3.8137724 | I36: =(G36-E36)/E36
A37: Round bowl 45cm with cover | C37: 609 | D37: 2.233 | E37: 2.8902 | F37: 3.5017536 | G37: 4.2021044 | I37: =(G37-E37)/E37
A38: Oval bowl 16L | C38: 625 | D38: 1.2705 | E38: 1.7177 | F38: 2.1533786 | G38: 2.5840544 | I38: =(G38-E38)/E38
A39: Square bowl 30cm | C39: 649 | D39: 0.6545 | E39: 0.9673 | F39: 1.2904186 | G39: 1.5485024 | I39: =(G39-E39)/E39
... A142: 24cm Round Plate | C142: 4002 | D142: 0.231 | E142: 0.4514 | F142: 0.69713363 | G142: 0.83656035 | I142: =(G142-E142)/E142
A143: 18cm Oval Plate | D143: 0.1155 | E143: 0.3107 | F143: 0.53532863 | G143: 0.64239435 | I143: =(G143-E143)/E143
A144: 24cm Oval Plate | D144: 0.154 | E144: 0.3576 | F144: 0.58926363 | G144: 0.70711635 | I144: =(G144-E144)/E144
A145: 29cm Oval Plate | D145: 0.2695 | E145: 0.4983 | F145: 0.75106863 | G145: 0.90128235 | I145: =(G145-E145)/E145
A146: Divided Plate | C146: 1207 | D146: 0.693 | E146: 1.0142 | F146: 1.3443536 | G146: 1.6132244 | I146: =(G146-E146)/E146
A147: 1.25 Oval Food Container | C147: 1312 | D147: 0.3465 | E147: 0.5921 | F147: 0.85893863 | G147: 1.0307264 | I147: =(G147-E147)/E147
A148: 1.75L Oval Food Container | C148: 1313 | D148: 0.5005 | E148: 0.7797 | F148: 1.0746786 | G148: 1.2896144 | I148: =(G148-E148)/E148
A149: 2.5L Oval Food Container | C149: 1341 | D149: 0.539 | E149: 0.8266 | F149: 1.1286136 | G149: 1.3543364 | I149: =(G149-E149)/E149
A150: 3.5L Oval Food Container | C150: 1316 | D150: 0.616 | E150: 0.9204 | F150: 1.2364836 | G150: 1.4837804 | I150: =(G150-E150)/E150
A151: 4.5L Oval Food Container | C151: 1342 | D151: 0.77 | E151: 1.108 | F151: 1.4522236 | G151: 1.7426684 | I151: =(G151-E151)/E151
A152: 5.5L Oval Food Container | C152: 1314 | D152: 1.0395 | E152: 1.4363 | F152: 1.8297686 | G152: 2.1957224 | I152: =(G152-E152)/E152
A153: Small Salad Bowl | C153: 1208 | D153: 0.1155 | E153: 0.3107 | F153: 0.53532863 | G153: 0.64239435 | I153: =(G153-E153)/E153
A154: Medium Salad Bowl | C154: 1209 | D154: 0.308 | E154: 0.5452 | F154: 0.80500363 | G154: 0.96600435 | I154: =(G154-E154)/E154
A155: Large Salad Bowl | C155: 1210 | D155: 0.8085 | E155: 1.1549 | F155: 1.5061586 | G155: 1.8073904 | I155: =(G155-E155)/E155
A156: Shoe Rack Single | C156: 2764 | D156: 5.1975 | E156: 6.5015 | F156: 7.6547486 | G156: 9.1856984 | I156: =(G156-E156)/E156
A157: Shoe Rack Double | C157: 2763 | D157: 8.701 | E157: 10.7694 | F157: 12.562834 | G157: 15.0754 | I157: =(G157-E157)/E157
... A174: 80*40cm Rectangular Planter with Tray | C174: 1816 | D174: 6.4295 | E174: 8.0023 | F174: 9.3806686 | G174: 11.256802 | I174: =(G174-E174)/E174

Sheet Staff Plan 
A1: NORCO / Vestwoods Egypt — Staffing Plan & Monthly Payroll (USD)
A2: Phased hiring plan | Base salaries (pre-15% benefits) | Year 1 monthly detail | Years 2-5 annual summary
A4: ROLE | B4: Monthly Salary (USD) | C4: Aug-26 | D4: Sep-26 | E4: Oct-26 | F4: Nov-26 | G4: Dec-26 | H4: Jan-27 | I4: Feb-27 | J4: Mar-27 | K4: Apr-27 | L4: May-27 | M4: Jun-27 | N4: Jul-27 | O4: Y1 Total
A5: CEO / Director | B5: 8000 | C5: 8000 | D5: 8000 | E5: 8000 | F5: 8000 | G5: 8000 | H5: 8000 | I5: 8000 | J5: 8000 | K5: 8000 | L5: 8000 | M5: 8000 | N5: 8000 | O5: =SUM(C5:N5)
A6: Financial Manager | B6: 4000 | C6: 4000 | D6: 4000 | E6: 4000 | F6: 4000 | G6: 4000 | H6: 4000 | I6: 4000 | J6: 4000 | K6: 4000 | L6: 4000 | M6: 4000 | N6: 4000 | O6: =SUM(C6:N6)
A7: Operations Manager | B7: 4000 | C7: 4000 | D7: 4000 | E7: 4000 | F7: 4000 | G7: 4000 | H7: 4000 | I7: 4000 | J7: 4000 | K7: 4000 | L7: 4000 | M7: 4000 | N7: 4000 | O7: =SUM(C7:N7)
A8: Marketing Manager | B8: 1500 | C8: – | D8: – | E8: 1500 | F8: 1500 | G8: 1500 | H8: 1500 | I8: 1500 | J8: 1500 | K8: 1500 | L8: 1500 | M8: 1500 | N8: 1500 | O8: =SUM(C8:N8)
A9: HR Manager | B9: 1000 | C9: – | D9: – | E9: 1000 | F9: 1000 | G9: 1000 | H9: 1000 | I9: 1000 | J9: 1000 | K9: 1000 | L9: 1000 | M9: 1000 | N9: 1000 | O9: =SUM(C9:N9)
A10: Sales Manager | B10: 3000 | C10: – | D10: 3000 | E10: 3000 | F10: 3000 | G10: 3000 | H10: 3000 | I10: 3000 | J10: 3000 | K10: 3000 | L10: 3000 | M10: 3000 | N10: 3000 | O10: =SUM(C10:N10)
A11: Warehouse Manager | B11: 1200 | C11: 1200 | D11: 1200 | E11: 1200 | F11: 1200 | G11: 1200 | H11: 1200 | I11: 1200 | J11: 1200 | K11: 1200 | L11: 1200 | M11: 1200 | N11: 1200 | O11: =SUM(C11:N11)
A12: Accountant #1 | B12: 800 | C12: – | D12: 800 | E12: 800 | F12: 800 | G12: 800 | H12: 800 | I12: 800 | J12: 800 | K12: 800 | L12: 800 | M12: 800 | N12: 800 | O12: =SUM(C12:N12)
A13: Accountant #2 | B13: 800 | C13: – | D13: – | E13: – | F13: – | G13: – | H13: – | I13: – | J13: 800 | K13: 800 | L13: 800 | M13: 800 | N13: 800 | O13: =SUM(C13:N13)
A14: Showroom Manager #1 | B14: 500 | C14: 500 | D14: 500 | E14: 500 | F14: 500 | G14: 500 | H14: 500 | I14: 500 | J14: 500 | K14: 500 | L14: 500 | M14: 500 | N14: 500 | O14: =SUM(C14:N14)
A15: Showroom Manager #2 | B15: 800 | D15: 800 | E15: 800 | F15: 800 | G15: 800 | H15: 800 | I15: 800 | J15: 800 | K15: 800 | L15: 800 | M15: 800 | N15: 800 | O15: =SUM(C15:N15)
A16: Sales Staff #1 | B16: 600 | C16: – | D16: – | E16: 600 | F16: 600 | G16: 600 | H16: 600 | I16: 600 | J16: 600 | K16: 600 | L16: 600 | M16: 600 | N16: 600 | O16: =SUM(C16:N16)
A17: Sales Staff #2 | B17: 600 | C17: – | D17: – | E17: – | F17: 600 | G17: 600 | H17: 600 | I17: 600 | J17: 600 | K17: 600 | L17: 600 | M17: 600 | N17: 600 | O17: =SUM(C17:N17)
A18: Sales Staff #3 | B18: 600 | C18: – | D18: – | E18: – | F18: – | G18: – | H18: 600 | I18: 600 | J18: 600 | K18: 600 | L18: 600 | M18: 600 | N18: 600 | O18: =SUM(C18:N18)
A19: Sales Staff #4 | B19: 600 | C19: – | D19: – | E19: – | F19: – | G19: – | H19: – | I19: – | J19: 600 | K19: 600 | L19: 600 | M19: 600 | N19: 600 | O19: =SUM(C19:N19)
A20: Driver #1 | B20: 500 | C20: 500 | D20: 500 | E20: 500 | F20: 500 | G20: 500 | H20: 500 | I20: 500 | J20: 500 | K20: 500 | L20: 500 | M20: 500 | N20: 500 | O20: =SUM(C20:N20)
A21: Driver #2 | B21: 500 | C21: – | D21: – | E21: – | F21: 500 | G21: 500 | H21: 500 | I21: 500 | J21: 500 | K21: 500 | L21: 500 | M21: 500 | N21: 500 | O21: =SUM(C21:N21)
A22: Administrative Asst #1 | B22: 600 | C22: 600 | D22: 600 | E22: 600 | F22: 600 | G22: 600 | H22: 600 | I22: 600 | J22: 600 | K22: 600 | L22: 600 | M22: 600 | N22: 600 | O22: =SUM(C22:N22)
A23: Administrative Asst #2 | B23: 600 | C23: – | D23: – | E23: – | F23: – | G23: – | H23: 600 | I23: 600 | J23: 600 | K23: 600 | L23: 600 | M23: 600 | N23: 600 | O23: =SUM(C23:N23)
A24: Warehouse Staff #1 | B24: 600 | C24: – | D24: – | E24: – | F24: 600 | G24: 600 | H24: 600 | I24: 600 | J24: 600 | K24: 600 | L24: 600 | M24: 600 | N24: 600 | O24: =SUM(C24:N24)
A25: Warehouse Staff #2 | B25: 600 | C25: – | D25: – | E25: – | F25: – | G25: – | H25: – | I25: – | J25: 600 | K25: 600 | L25: 600 | M25: 600 | N25: 600 | O25: =SUM(C25:N25)
A26: TOTAL BASE SALARIES | C26: =SUM(C5:C25) | D26: =SUM(D5:D25) | E26: =SUM(E5:E25) | F26: =SUM(F5:F25) | G26: =SUM(G5:G25) | H26: =SUM(H5:H25) | I26: =SUM(I5:I25) | J26: =SUM(J5:J25) | ... O26: =SUM(O5:O25)
A27: Social Insurance & Benefits (15%) | B27: 15% | C27: =C26*15% | D27: =D26*15% | E27: =E26*15% | F27: =F26*15% | G27: =G26*15% | H27: =H26*15% | I27: =I26*15% | J27: =J26*15% | ... O27: =O26*15%
A28: TOTAL PERSONNEL COSTS (incl. benefits) | C28: =SUM(C26:C27) | D28: =SUM(D26:D27) | E28: =SUM(E26:E27) | F28: =SUM(F26:F27) | G28: =SUM(G26:G27) | H28: =SUM(H26:H27) | I28: =SUM(I26:I27) | J28: =SUM(J26:J27) | ... O28: =SUM(O26:O27)
A29: Total Headcount (end of month) | B29: Month-end | C29: 6 | D29: 8 | E29: 11 | F29: 14 | G29: 14 | H29: 16 | I29: 16 | J29: 19 | K29: 19 | L29: 19 | M29: 19 | N29: 19 | O29: 19
A33: YEAR 2 (Aug 2027 – Jul 2028) — 26 Staff
A34: Role | B34: Monthly Salary (USD) | C34: Annual Salary (USD) | D34: Status
A35: MANAGEMENT
A36: CEO / Director | B36: 8000 | C36: =B36*12 | D36: Existing
A37: Financial Manager | B37: 4000 | C37: =B37*12 | D37: Existing
A38: Operations Manager | B38: 4000 | C38: =B38*12 | D38: Existing
A39: Sales Manager | B39: 3000 | C39: =B39*12 | D39: Existing
A40: Marketing Manager | B40: 1500 | C40: =B40*12 | D40: Existing
A41: HR Manager | B41: 1000 | C41: =B41*12 | D41: Existing
A42: FINANCE & ADMIN
A43: Accountant #1 | B43: 800 | C43: =B43*12 | D43: Existing
A44: Accountant #2 | B44: 800 | C44: 9600 | D44: Existing
A45: Administrative Asst #1 | B45: 600 | C45: =B45*12 | D45: Existing
A46: Administrative Asst #2 | B46: 600 | C46: 7200 | D46: Existing
A47: Administrative Asst #3 | B47: 600 | C47: 7200 | D47: NEW
A48: WAREHOUSE & LOGISTICS
A49: Warehouse Manager | B49: 1200 | C49: =B49*12 | D49: Existing
A50: Warehouse Staff #1 | B50: 600 | C50: 7200 | D50: Existing
A51: Warehouse Staff #2 | B51: 600 | C51: 7200 | D51: Existing
A52: Logistics Coordinator | B52: 1200 | C52: 14400 | D52: NEW
A53: SALES
A54: Sales Staff #1 | B54: 600 | C54: 7200 | D54: Existing
A55: Sales Staff #2 | B55: 600 | C55: 7200 | D55: Existing
A56: Sales Staff #3 | B56: 600 | C56: 7200 | D56: Existing
A57: Sales Staff #4 | B57: 600 | C57: 7200 | D57: Existing
A58: Sales Staff #5 | B58: 600 | C58: 7200 | D58: NEW
A59: Sales Staff #6 | B59: 600 | C59: 7200 | D59: NEW
A60: TECHNICAL & SERVICE
A61: Customer Service Manager | B61: 1500 | C61: =B61*12 | D61: NEW
A62: Technical Specialist | B62: 1200 | C62: 14400 | D62: NEW
A63: DRIVERS
A64: Driver #1 | B64: 500 | C64: =B64*12 | D64: Existing
A65: Driver #2 | B65: 500 | C65: 6000 | D65: Existing
A66: Driver #3 | B66: 500 | C66: 6000 | D66: NEW
A68: Total Base Salaries (annual): | C68: =SUM(C64:C66,C61:C62,C54:C59,C49:C52,C43:C47,C36:C41)
A69: Social Insurance & Benefits (15%): | C69: =C68*15%
A70: Personnel Sub-total (base + benefits): | C70: =SUM(C68:C69)
A71: Sales Commissions (4% of Egypt revenue $3,119,380): | C71: =4%*'Annual P&L Summary Y1-Y5'!C6
A72: TOTAL ANNUAL PERSONNEL COST: | C72: =SUM(C70:C71)
A75: YEAR 3 (Aug 2028 – Jul 2029) — 35 Staff
A76: Role | B76: Monthly Salary (USD) | C76: Annual Salary (USD) | D76: Status
A77: MANAGEMENT
A78: CEO / Director | B78: 8000 | C78: =B78*12 | D78: Existing
A79: Financial Manager | B79: 4000 | C79: 48000 | D79: Existing
A80: Operations Manager | B80: 4000 | C80: 48000 | D80: Existing
A81: Sales Manager | B81: 3000 | C81: 36000 | D81: Existing
A82: Marketing Manager | B82: 1500 | C82: 18000 | D82: Existing
A83: HR Manager | B83: 1000 | C83: 12000 | D83: Existing
A84: Alexandria Branch Manager | B84: 2000 | C84: 24000 | D84: NEW
A85: FINANCE & ADMIN
A86: Accountant #1 | B86: 800 | C86: 9600 | D86: Existing
A87: Accountant #2 | B87: 800 | C87: 9600 | D87: Existing
A88: Finance Analyst | B88: 1000 | C88: 12000 | D88: NEW
A89: Administrative Asst #1 | B89: 600 | C89: 7200 | D89: Existing
A90: Administrative Asst #2 | B90: 600 | C90: 7200 | D90: Existing
A91: Administrative Asst #3 | B91: 600 | C91: 7200 | D91: Existing
A92: WAREHOUSE & LOGISTICS
A93: Warehouse Manager | B93: 1200 | C93: 14400 | D93: Existing
A94: Warehouse Staff #1 | B94: 600 | C94: 7200 | D94: Existing
A95: Warehouse Staff #2 | B95: 600 | C95: 7200 | D95: Existing
A96: Logistics Coordinator | B96: 1200 | C96: 14400 | D96: Existing
A97: Supply Chain Analyst | B97: 1000 | C97: 12000 | D97: NEW
A98: SALES
A99: Sales Staff #1 | B99: 600 | C99: 7200 | D99: Existing
A100: Sales Staff #2 | B100: 600 | C100: 7200 | D100: Existing
A101: Sales Staff #3 | B101: 600 | C101: 7200 | D101: Existing
A102: Sales Staff #4 | B102: 600 | C102: 7200 | D102: Existing
A103: Sales Staff #5 | B103: 600 | C103: 7200 | D103: Existing
A104: Sales Staff #6 | B104: 600 | C104: 7200 | D104: Existing
A105: Senior Sales Executive | B105: 1200 | C105: 14400 | D105: NEW
A106: Alex Sales Staff #1 | B106: 600 | C106: 7200 | D106: NEW
A107: Alex Sales Staff #2 | B107: 600 | C107: 7200 | D107: NEW
...

Sheet Monthly P&L Year 1
A1: NORCO General Trading L.L.C. — Vestwoods Egypt 5-Year Business Plan
A2: Monthly Profit & Loss Statement — Year 1 (August 2026 – July 2027) | All figures in USD
A4: DESCRIPTION | B4: Aug-26 | C4: Sep-26 | D4: Oct-26 | E4: Nov-26 | F4: Dec-26 | G4: Jan-27 | H4: Feb-27 | I4: Mar-27 | J4: Apr-27 | K4: May-27 | L4: Jun-27 | M4: Jul-27 | N4: TOTAL Year 1
A5: REVENUE
A6: Egypt - Vestwoods Sales | B6: 20000 | C6: 40000 | D6: 119483 | E6: 200000 | F6: 220000 | G6: 230000 | H6: 220000 | I6: 230000 | J6: 270000 | K6: 300000 | L6: 350000 | M6: 400000 | N6: =SUM(B6:M6)
A7: Sudan - Vestwoods Sales | B7: 0 | C7: 0 | D7: 0 | E7: 0 | F7: 0 | G7: 393861 | H7: 0 | I7: 393861 | J7: 0 | K7: 393861 | L7: 0 | M7: 393861 | N7: =SUM(B7:M7)
A8: Algeria - Vestwoods Sales (from M8 - LC) | B8: 0 | C8: 0 | D8: 0 | E8: 0 | F8: 0 | G8: 0 | H8: 0 | I8: 393861 | J8: 0 | K8: 393861 | L8: 0 | M8: 393861 | N8: =SUM(B8:M8)
A9: Egypt - Al Reem Plastics Sales | C9: 20000 | D9: 30000 | E9: 40000 | F9: 50000 | G9: 50000 | H9: 50000 | I9: 56883 | J9: 50000 | K9: 70000 | L9: 80000 | M9: 80000 | N9: =SUM(B9:M9)
A10: Sudan - Al Reem Plastics Sales | G10: 52444 | I10: 52444 | K10: =52444*2 | M10: 52444 | N10: =SUM(B10:M10)
A11: TOTAL REVENUE | B11: =SUM(B6:B10) | C11: =SUM(C6:C10) | D11: =SUM(D6:D10) | E11: =SUM(E6:E10) | F11: =SUM(F6:F10) | G11: =SUM(G6:G10) | H11: =SUM(H6:H10) | I11: =SUM(I6:I10) | ... N11: =SUM(N6:N10)
A12: COST OF GOODS SOLD
A13: Egypt Product Cost (79% of Egypt Sales — 50% I LOCK wholesale + 50% direct retail) | B13: 15800 | C13: 31600 | D13: 94391.6 | E13: 158000 | F13: 173800 | G13: 181700 | H13: 173800 | I13: 181700 | J13: 213300 | K13: 237000 | L13: 276500 | M13: 316000 | N13: =SUM(B13:M13)
A14: Sudan Product Cost (50% of Sudan Sales) | B14: =B7*50% | C14: =C7*50% | D14: =D7*50% | E14: =E7*50% | F14: =F7*50% | G14: =G7*50% | H14: =H7*50% | I14: =I7*50% | ... M14: =M7*50% | N14: =SUM(B14:M14)
A15: Algeria COGS (50%) | B15: =B8*50% | C15: =C8*50% | D15: =D8*50% | E15: =E8*50% | F15: =F8*50% | G15: =G8*50% | H15: =H8*50% | I15: =I8*50% | ... M15: =M8*50% | N15: =SUM(B15:M15)
A16: Egypt - Al Reem Plastics COGS (75%) | B16: 0 | C16: 15000 | D16: 22500 | E16: 30000 | F16: 37500 | G16: 37500 | H16: 37500 | I16: 42662.2 | J16: 37500 | K16: 52500 | L16: 60000 | M16: 60000 | N16: =SUM(B16:M16)
A17: Sudan - Al Reem Plastics COGS (82.64%) | B17: 0 | C17: 0 | D17: 0 | E17: 0 | F17: 0 | G17: 43339.7 | H17: 0 | I17: 43339.7 | J17: 0 | K17: 86679.4 | L17: 0 | M17: 43339.7 | N17: =SUM(B17:M17)
A18: TOTAL COGS | B18: 15800 | C18: 46600 | D18: 116891.6 | E18: 188000 | F18: 211300 | G18: 459470.2 | H18: 211300 | I18: 661562.9 | J18: 250800 | K18: 770040.4 | L18: 336500 | M18: 813200.7 | N18: =SUM(B18:M18)
A19: GROSS PROFIT | B19: 4200 | C19: 13400 | D19: 32591.4 | E19: 52000 | F19: 58700 | G19: 266834.8 | H19: 58700 | I19: 465486.1 | J19: 69200 | K19: 492569.6 | L19: 93500 | M19: 506965.3 | N19: =SUM(B19:M19)
A20: Gross Margin % | B20: 0.21 | C20: 0.223 | D20: 0.218 | E20: 0.217 | F20: 0.217 | G20: 0.367 | H20: 0.217 | I20: 0.413 | J20: 0.216 | K20: 0.39 | L20: 0.217 | M20: 0.384 | N20: 0.341
A21: OPERATING EXPENSES — PERSONNEL COSTS
A22: CEO / Managing Director | B22: 8000 | C22: 8000 | D22: 8000 | E22: 8000 | F22: 8000 | G22: 8000 | H22: 8000 | I22: 8000 | J22: 8000 | K22: 8000 | L22: 8000 | M22: 8000 | N22: =SUM(B22:M22)
A23: CFO | B23: 4000 | C23: 4000 | D23: 4000 | E23: 4000 | F23: 4000 | G23: 4000 | H23: 4000 | I23: 4000 | J23: 4000 | K23: 4000 | L23: 4000 | M23: 4000 | N23: =SUM(B23:M23)
A24: COO | B24: 4000 | C24: 4000 | D24: 4000 | E24: 4000 | F24: 4000 | G24: 4000 | H24: 4000 | I24: 4000 | J24: 4000 | K24: 4000 | L24: 4000 | M24: 4000 | N24: =SUM(B24:M24)
A25: Director of Marketing | D25: 1500 | E25: 1500 | F25: 1500 | G25: 1500 | H25: 1500 | I25: 1500 | J25: 1500 | K25: 1500 | L25: 1500 | M25: 1500 | N25: =SUM(B25:M25)
A26: HR Manager | D26: 1000 | E26: 1000 | F26: 1000 | G26: 1000 | H26: 1000 | I26: 1000 | J26: 1000 | K26: 1000 | L26: 1000 | M26: 1000 | N26: =SUM(B26:M26)
A27: Director of Sales | C27: 3000 | D27: 3000 | E27: 3000 | F27: 3000 | G27: 3000 | H27: 3000 | I27: 3000 | J27: 3000 | K27: 3000 | L27: 3000 | M27: 3000 | N27: =SUM(B27:M27)
A28: Warehouse Manager | B28: 1200 | C28: 1200 | D28: 1200 | E28: 1200 | F28: 1200 | G28: 1200 | H28: 1200 | I28: 1200 | J28: 1200 | K28: 1200 | L28: 1200 | M28: 1200 | N28: =SUM(B28:M28)
A29: Accountant #1 | C29: 800 | D29: 800 | E29: 800 | F29: 800 | G29: 800 | H29: 800 | I29: 800 | J29: 800 | K29: 800 | L29: 800 | M29: 800 | N29: =SUM(B29:M29)
A30: Accountant #2 | I30: 800 | J30: 800 | K30: 800 | L30: 800 | M30: 800 | N30: =SUM(B30:M30)
A31: Showroom Manager #1 | B31: 500 | C31: 500 | D31: 500 | E31: 500 | F31: 500 | G31: 500 | H31: 500 | I31: 500 | J31: 500 | K31: 500 | L31: 500 | M31: 500 | N31: =SUM(B31:M31)
A32: Showroom Manager #2 | C32: 800 | D32: 800 | E32: 800 | F32: 800 | G32: 800 | H32: 800 | I32: 800 | J32: 800 | K32: 800 | L32: 800 | M32: 800 | N32: =SUM(B32:M32)
A33: Sales Staff #1 | D33: 600 | E33: 600 | F33: 600 | G33: 600 | H33: 600 | I33: 600 | J33: 600 | K33: 600 | L33: 600 | M33: 600 | N33: =SUM(B33:M33)
A34: Sales Staff #2 | E34: 600 | F34: 600 | G34: 600 | H34: 600 | I34: 600 | J34: 600 | K34: 600 | L34: 600 | M34: 600 | N34: =SUM(B34:M34)
A35: Sales Staff #3 | G35: 600 | H35: 600 | I35: 600 | J35: 600 | K35: 600 | L35: 600 | M35: 600 | N35: =SUM(B35:M35)
A36: Sales Staff #4 | I36: 600 | J36: 600 | K36: 600 | L36: 600 | M36: 600 | N36: =SUM(B36:M36)
A37: Driver #1 | B37: 500 | C37: 500 | D37: 500 | E37: 500 | F37: 500 | G37: 500 | H37: 500 | I37: 500 | J37: 500 | K37: 500 | L37: 500 | M37: 500 | N37: =SUM(B37:M37)
A38: Driver #2 | E38: 500 | F38: 500 | G38: 500 | H38: 500 | I38: 500 | J38: 500 | K38: 500 | L38: 500 | M38: 500 | N38: =SUM(B38:M38)
A39: Administrative Asst #1 | B39: 600 | C39: 600 | D39: 600 | E39: 600 | F39: 600 | G39: 600 | H39: 600 | I39: 600 | J39: 600 | K39: 600 | L39: 600 | M39: 600 | N39: =SUM(B39:M39)
A40: Administrative Asst #2 | G40: 600 | H40: 600 | I40: 600 | J40: 600 | K40: 600 | L40: 600 | M40: 600 | N40: =SUM(B40:M40)
A41: Warehouse Staff #1 | E41: 600 | F41: 600 | G41: 600 | H41: 600 | I41: 600 | J41: 600 | K41: 600 | L41: 600 | M41: 600 | N41: =SUM(B41:M41)
A42: Warehouse Staff #2 | I42: 600 | J42: 600 | K42: 600 | L42: 600 | M42: 600 | N42: =SUM(B42:M42)
A43: Total Base Salaries | B43: =SUM(B22:B42) | C43: =SUM(C22:C42) | D43: =SUM(D22:D42) | E43: =SUM(E22:E42) | F43: =SUM(F22:F42) | G43: =SUM(G22:G42) | H43: =SUM(H22:H42) | I43: =SUM(I22:I42) | ... M43: =SUM(M22:M42) | N43: =SUM(B43:M43)
A44: Social Insurance & Benefits (15%) | B44: =B43*15% | C44: =C43*15% | D44: =D43*15% | E44: =E43*15% | F44: =F43*15% | G44: =G43*15% | H44: =H43*15% | I44: =I43*15% | ... M44: =M43*15% | N44: =SUM(B44:M44)
A45: TOTAL PERSONNEL COSTS (base + benefits) | B45: =SUM(B43:B44) | C45: =SUM(C43:C44) | D45: =SUM(D43:D44) | E45: =SUM(E43:E44) | F45: =SUM(F43:F44) | G45: =SUM(G43:G44) | H45: =SUM(H43:H44) | I45: =SUM(I43:I44) | ... N45: =SUM(N43:N44)
A46: Sales Commissions (4% Vestwoods + 3% Al Reem, Egypt sales) | B46: 800 | C46: 2200 | D46: 5679.3 | E46: 9200 | F46: 10300 | G46: 10700 | H46: 10300 | I46: 10906.5 | J46: 12300 | K46: 14100 | L46: 16400 | M46: 18400 | N46: =SUM(B46:M46)
A47: TOTAL PERSONNEL INCL. COMMISSIONS | B47: 22420 | C47: 29110 | D47: 36154.3 | E47: 41630 | F47: 42730 | G47: 44510 | H47: 44110 | I47: 47016.5 | J47: 48410 | K47: 50210 | L47: 52510 | M47: 54510 | N47: =SUM(B47:M47)
A48: OPERATING EXPENSES — FACILITIES
A49: Showroom Rent — 6th October City (EGP 10,000/mo = USD 200) [EXISTING] | B49: 200 | C49: 200 | D49: 200 | E49: 200 | F49: 200 | G49: 200 | H49: 200 | I49: 200 | J49: 200 | K49: 200 | L49: 200 | M49: 200 | N49: =SUM(B49:M49)
A50: Showroom Rent — New Cairo / Fifth Settlement (~50 sqm, USD 2,500/mo) [NEW — post-investment] | B50: 2500 | C50: 2500 | D50: 2500 | E50: 2500 | F50: 2500 | G50: 2500 | H50: 2500 | I50: 2500 | J50: 2500 | K50: 2500 | L50: 2500 | M50: 2500 | N50: =SUM(B50:M50)
A51: Office Rent — Fifth Settlement (100 sqm) | B51: 6000 | C51: 3000 | D51: 3000 | E51: 3000 | F51: 3000 | G51: 3000 | H51: 3000 | I51: 3000 | J51: 3000 | K51: 3000 | L51: 3000 | M51: 3000 | N51: =SUM(B51:M51)
A52: Warehouse Rent — 6th October City (~400 sqm) | B52: 3000 | C52: 3000 | D52: 3000 | E52: 3000 | F52: 3000 | G52: 3000 | H52: 3000 | I52: 3000 | J52: 3000 | K52: 3000 | L52: 3000 | M52: 3000 | N52: =SUM(B52:M52)
A53: Utilities (Electricity, Water, Internet) | B53: 400 | C53: 400 | D53: 700 | E53: 700 | F53: 700 | G53: 700 | H53: 700 | I53: 700 | J53: 700 | K53: 700 | L53: 700 | M53: 700 | N53: =SUM(B53:M53)
A54: TOTAL FACILITIES | B54: =SUM(B49:B53) | C54: =SUM(C49:C53) | D54: =SUM(D49:D53) | E54: =SUM(E49:E53) | F54: =SUM(F49:F53) | G54: =SUM(G49:G53) | H54: =SUM(H49:H53) | I54: =SUM(I49:I53) | ... N54: =SUM(N49:N53)
A55: OPERATING EXPENSES — OPERATIONS
A56: Vehicle & Fuel Costs (2 trucks) | B56: 800 | C56: 800 | D56: 800 | E56: 1500 | F56: 1500 | G56: 1500 | H56: 1500 | I56: 1500 | J56: 1500 | K56: 1500 | L56: 1500 | M56: 1500 | N56: =SUM(B56:M56)
A57: TOTAL OPERATIONS | B57: =SUM(B56) | C57: =SUM(C56) | D57: =SUM(D56) | E57: =SUM(E56) | F57: =SUM(F56) | G57: =SUM(G56) | H57: =SUM(H56) | I57: =SUM(I56) | ... M57: =SUM(M56) | N57: =SUM(B57:M57)
A58: OPERATING EXPENSES — MARKETING & PROMOTIONS
A59: Advertising & Digital Marketing (M3 Exhibition) | B59: 5000 | C59: 5000 | D59: 11000 | E59: 4000 | F59: 3500 | G59: 3000 | H59: 3000 | I59: 3000 | J59: 2500 | K59: 2500 | L59: 2500 | M59: 2500 | N59: =SUM(B59:M59)
A60: Printing & Brochures | B60: 1000 | C60: 300 | D60: 300 | E60: 300 | F60: 300 | G60: 300 | H60: 300 | I60: 300 | J60: 300 | K60: 300 | L60: 300 | M60: 300 | N60: =SUM(B60:M60)
A61: Giveaways & Product Samples | B61: 1000 | C61: 1000 | D61: 700 | E61: 700 | F61: 600 | G61: 600 | H61: 600 | I61: 600 | J61: 500 | K61: 500 | L61: 500 | M61: 500 | N61: =SUM(B61:M61)
A62: TOTAL MARKETING | B62: =SUM(B59:B61) | C62: =SUM(C59:C61) | D62: =SUM(D59:D61) | E62: =SUM(E59:E61) | F62: =SUM(F59:F61) | G62: =SUM(G59:G61) | H62: =SUM(H59:H61) | I62: =SUM(I59:I61) | ... N62: =SUM(N59:N61)
A63: OPERATING EXPENSES — GENERAL & ADMINISTRATIVE
A64: Professional Fees (Legal, Audit, Consulting) | B64: 3000 | C64: 2000 | D64: 2000 | E64: 1000 | F64: 1000 | G64: 1000 | H64: 1000 | I64: 1000 | J64: 1000 | K64: 1000 | L64: 1000 | M64: 1000 | N64: =SUM(B64:M64)
A65: Insurance | B65: 2000 | C65: 200 | D65: 200 | E65: 200 | F65: 200 | G65: 200 | H65: 200 | I65: 200 | J65: 200 | K65: 200 | L65: 200 | M65: 200 | N65: =SUM(B65:M65)
A66: Communication (Phone, Internet) | B66: 400 | C66: 400 | D66: 400 | E66: 400 | F66: 400 | G66: 400 | H66: 400 | I66: 400 | J66: 400 | K66: 400 | L66: 400 | M66: 400 | N66: =SUM(B66:M66)
A67: Travel & Business Entertainment | B67: 1500 | C67: 1500 | D67: 1500 | E67: 1000 | F67: 1000 | G67: 1000 | H67: 800 | I67: 800 | J67: 800 | K67: 800 | L67: 800 | M67: 800 | N67: =SUM(B67:M67)
A68: Bank Charges & Transfer Fees | B68: 300 | C68: 300 | D68: 300 | E68: 300 | F68: 300 | G68: 300 | H68: 300 | I68: 300 | J68: 300 | K68: 300 | L68: 300 | M68: 300 | N68: =SUM(B68:M68)
A69: Government Fees & Licensing (GOEI, etc.) | B69: 3000 | C69: 2000 | D69: 2000 | E69: 500 | F69: 500 | G69: 300 | H69: 300 | I69: 300 | J69: 300 | K69: 300 | L69: 300 | M69: 300 | N69: =SUM(B69:M69)
A70: Miscellaneous | B70: 500 | C70: 500 | D70: 500 | E70: 500 | F70: 500 | G70: 500 | H70: 500 | I70: 500 | J70: 500 | K70: 500 | L70: 500 | M70: 500 | N70: =SUM(B70:M70)
A71: TOTAL G&A | B71: =SUM(B64:B70) | C71: =SUM(C64:C70) | D71: =SUM(D64:D70) | E71: =SUM(E64:E70) | F71: =SUM(F64:F70) | G71: =SUM(G64:G70) | H71: =SUM(H64:H70) | I71: =SUM(I64:I70) | ... N71: =SUM(N64:N70)
A72: DEPRECIATION & AMORTISATION
A73: Fit-out & Equipment Amortisation (3-yr straight line) | B73: 1400 | C73: 1400 | D73: 1400 | E73: 1400 | F73: 1400 | G73: 1400 | H73: 1400 | I73: 1400 | J73: 1400 | K73: 1400 | L73: 1400 | M73: 1400 | N73: =SUM(B73:M73)
A74: TOTAL D&A | B74: =B73 | C74: =C73 | D74: =D73 | E74: =E73 | F74: =F73 | G74: =G73 | H74: =H73 | I74: =I73 | ... M74: =M73 | N74: =SUM(B74:M74)
A75: TOTAL OPERATING EXPENSES | B75: 54420 | C75: 53610 | D75: 66654.3 | E75: 62830 | F75: 63330 | G75: 64410 | H75: 63810 | I75: 66716.5 | J75: 67510 | K75: 69310 | L75: 71610 | M75: 73610 | N75: =SUM(B75:M75)
A76: EARNINGS BEFORE INTEREST & TAX (EBIT) | B76: -50220 | C76: -40210 | D76: -34062.9 | E76: -10830 | F76: -4630 | G76: 202424.8 | H76: -5110 | I76: 398769.6 | J76: 1690 | K76: 423259.6 | L76: 21890 | M76: 433355.3 | N76: =SUM(B76:M76)
A77: Interest on Trade Finance (est.) | B77: 0 | C77: 500 | D77: 500 | E77: 500 | F77: 500 | G77: 500 | H77: 500 | I77: 500 | J77: 500 | K77: 500 | L77: 500 | M77: 500 | N77: =SUM(B77:M77)
A78: EARNINGS BEFORE TAX (EBT) | B78: -50220 | C78: -40710 | D78: -34562.9 | E78: -11330 | F78: -5130 | G78: 201924.8 | H78: -5610 | I78: 398269.6 | J78: 1190 | K78: 422759.6 | L78: 21390 | M78: 432855.3 | N78: =SUM(B78:M78)
A79: Corporate Income Tax (22.5% — with loss carry-forward) | B79: 0 | C79: 0 | D79: 0 | E79: 0 | F79: 0 | G79: 13493.7 | H79: 0 | I79: 88348.4 | J79: 267.7 | K79: 95120.9 | L79: 4812.8 | M79: 97392.4 | N79: =SUM(B79:M79)
A80: NET PROFIT / (LOSS) | B80: -50220 | C80: -40710 | D80: -34562.9 | E80: -11330 | F80: -5130 | G80: 188431.1 | H80: -5610 | I80: 309921.2 | J80: 922.3 | K80: 327638.7 | L80: 16577.2 | M80: 335462.9 | N80: =SUM(B80:M80)
A81: Net Margin % | B81: -2.511 | C81: -0.678 | D81: -0.231 | E81: -0.047 | F81: -0.019 | G81: 0.259 | H81: -0.021 | I81: 0.275 | J81: 0.003 | K81: 0.259 | L81: 0.039 | M81: 0.254 | N81: 0.166
A82: Cumulative Profit / (Loss) | B82: -50220 | C82: -90930 | D82: -125492.9 | E82: -136822.9 | F82: -141952.9 | G82: 46478.2 | H82: 40868.2 | I82: 350789.4 | J82: 351711.7 | K82: 679350.4 | L82: 695927.6 | M82: 1031390.5 | N82: 1031390.5
A84: KEY ASSUMPTIONS Vestwoods: Egypt COGS = 79% (50% I LOCK wholesale + 50% direct retail ) | Sudan COGS = 50% wholesale | Algeria COGS = 50% wholesale | Sales commissions = 4% of Egypt sales | Benefits = 15% of base salaries | Shipping = USD 6,865/40ft | EGP 53 = USD 1 | Egypt Y1 = 6 containers | Sudan Y1 = 4 containers | Algeria Y1 = 3 containers
A85: KEY ASSUMPTIONS Al Reem Plastics: Egypt COGS = 75% (50% wholesale + 50% direct retail ) | Sudan COGS = 82.64% wholesale | Sales commissions = 3% of Egypt sales | Benefits = 15% of base salaries | Shipping = USD 2,500/40ft | EGP 53 = USD 1 | Egypt Y1 = 10 containers | Sudan Y1 = 5 containers

Sheet Cash Flow Year 1
A1: NORCO / Vestwoods Egypt — Monthly Cash Flow Statement — Year 1 (August 2026 – July 2027)
A2: Vestwoods terms: After approval of Sinosure 10% deposit on PO + 90% at 3-month credit | Egypt customers: 30-60 day AR (1-month lag) | Sudan: 50% advance + 50% on delivery (=same month)
A4: CASH FLOW ITEM | B4: Aug-26 | C4: Sep-26 | D4: Oct-26 | E4: Nov-26 | F4: Dec-26 | G4: Jan-27 | H4: Feb-27 | I4: Mar-27 | J4: Apr-27 | K4: May-27 | L4: Jun-27 | M4: Jul-27 | N4: YEAR 1 TOTAL
A5: CASH INFLOWS
A6: Egypt Collections Vestwoods (1-month lag, 30-day avg) | B6: 20000 | C6: 40000 | D6: =100518-40000-20000 | E6: 55000 | F6: 80000 | G6: 130000 | H6: 180000 | I6: 270000 | J6: 330000 | K6: 380000 | L6: 420000 | M6: 440000 | N6: =SUM(B6:M6) | O6: =N6-'Monthly P&L Year 1'!N6
A7: Egypt Collections Al Reem Plastics | C7: 20000 | D7: 30000 | E7: 40000 | F7: 50000 | G7: 50000 | H7: 50000 | I7: 56883 | J7: 50000 | K7: 70000 | L7: 80000 | M7: 80000 | N7: =SUM(B7:M7) | O7: =N7-'Monthly P&L Year 1'!N9
A8: Sudan Cash Received Vestwoods (50% advance + 50% delivery) | G8: =393861/2 | H8: =393861/2 | I8: =393861/2 | J8: =393861/2 | K8: =393861/2 | L8: =393861/2 | M8: =393861/2 | N8: =SUM(B8:M8) | O8: =N8-'Monthly P&L Year 1'!N7
A9: Sudan Cash Received Al Reem Plastics 100% Downpayment | G9: 52444 | I9: 52444 | K9: =52444*2 | M9: 52444 | N9: =SUM(B9:M9)
A10: Algeria Cash Received (50% advance + 50% delivery) | I10: =393861/2 | J10: =393861/2 | K10: =393861/2 | L10: =393861/2 | M10: =393861/2 | N10: =SUM(B10:M10) | O10: =N10-'Monthly P&L Year 1'!N8
A11: Investor capital (T1 Aug 500K | T2 Nov 500K — USD 1.0M core) | B11: 500000 | E11: 500000 | N11: =SUM(B11:M11)
A12: TOTAL CASH INFLOWS | B12: =SUM(B6:B11) | C12: =SUM(C6:C11) | D12: =SUM(D6:D11) | E12: =SUM(E6:E11) | F12: =SUM(F6:F11) | G12: =SUM(G6:G11) | H12: =SUM(H6:H11) | I12: =SUM(I6:I11) | ... N12: =SUM(N6:N11)
A13: CASH OUTFLOWS
A14: Vestwoods 1st Container payment full | B14: 50000 | N14: =SUM(B14:M14)
A15: Vestwoods 2nd Container Deposits (50% Downpayment + 50% 60 days of BOL ) | C15: =342299/2 | N15: =SUM(B15:M15)
A16: Vestwoods 2nd Container second payment 50% 60 days | E16: =342299/2 | N16: =SUM(B16:M16)
A17: Vestwoods 3rd -4th (full downpayment) | F17: 342299 | G17: 342299 | N17: =SUM(B17:M17)
A18: Vestwoods 5th - 13th Container 10% downpayment | I18: =35000*2 | J18: 35000 | K18: =35000*3 | M18: =35000*2 | N18: =SUM(B18:M18)
A19: Vestwoods 5th - 13th Container Balance Payments (90% at 3-month credit) | K19: 315000 | L19: =315000*2 | M19: =315000*3 | N19: =SUM(B19:M19)
A20: Al Reem Plastics Credit Payment | D20: =43339*2 | F20: =43339*2 | G20: =43339 | H20: =36201+43339 | J20: =36201 | K20: =G20*2 | L20: =36201 | M20: =L20 | N20: =SUM(B20:M20)
A21: One-Time Setup Costs (fit-out, deposits, licenses, demos) | B21: 50000 | N21: =SUM(B21:M21)
A22: Operating Expenses (salaries, commissions, rent, marketing, G&A) | B22: 54420 | C22: 53610 | D22: 66654.3 | E22: 62830 | F22: 63330 | G22: 64410 | H22: 63810 | I22: 66716.5 | J22: 67510 | K22: 69310 | L22: 71610 | M22: 73610 | N22: =SUM(B22:M22)
A23: TOTAL CASH OUTFLOWS | B23: 154420 | C23: 224759.5 | D23: 153332.3 | E23: 233979.5 | F23: 492307 | G23: 450048 | H23: 143350 | I23: 136716.5 | J23: 138711 | K23: 575988 | L23: 737811 | M23: 1124811 | N23: =SUM(B23:M23)
A24: NET MONTHLY CASH FLOW | B24: 365580 | C24: -164759.5 | D24: -82814.3 | E24: 361020.5 | F24: -362307 | G24: -20673.5 | H24: 283580.5 | I24: 636471.5 | J24: 635150 | K24: 372761 | L24: 156050 | M24: -158506 | N24: =SUM(B24:M24)
A25: CUMULATIVE CASH POSITION | B25: 365580 | C25: 200820.5 | D25: 118006.2 | E25: 479026.7 | F25: 116719.7 | G25: 96046.2 | H25: 379626.7 | I25: 1016098.2 | J25: 1651248.2 | K25: 2024009.2 | L25: 2180059.2 | M25: 2021553.2 | N25: 2021553.2
A27: KEY CASH FLOW METRICS & INVESTOR NOTES
A28: Peak Cash Deficit (worst month) | B28: USD 903,954 — Jan-27 (excluding investor capital) | H28: Covered by the USD 1.0M raise; minimum cash USD 96,046 in Jan-27
A29: Batches 6–7 Container Balances (due Y2M1–M2) | B29: 3 × USD 315,000 = USD 945,000 due Aug–Oct 2027 (Y2 M1–M3) | H29: Plus the 9th 10% deposit (USD 35,000) and Al Reem payable (USD 158,571) — all covered by Y1 ending cash
A30: Egypt M12 Revenue Collected Y2M1 | B30: USD 500,000 | H30: July 2027 Egypt sales collected August 2027 — first Year 2 cash inflow
A31: Vestwoods Credit Benefit | B31: USD 3,024,000 deferred over 3 months | H31: 90% balance deferred across 14 containers — dramatically reduces working capital need
A32: Sudan Cash Flow Advantage | B32: 50% collected before shipment = same-month cash receipt | H32: Sudan 50% advance payment improves NORCO net funding by ~USD 640K in Year 1
A33: Required Initial Investment | B33: USD 1,000,000 core (500K + 500K) | H33: Covers the USD 903,954 peak deficit; optional USD 500K accelerator lifts buffer (ceiling 1.5M)
A34: Year 1 Ending Cash Position | B34: USD 2,021,553 | H34: Cash-flow positive from Feb-27 cumulative low; surplus funds Y2 container balances
A35: NOTE: Batches 6–7 container balances (USD 864,000 total) are due Year 2 Months 1–2 (Aug–Sep 2027). These are NOT included in Year 1 outflows above. They are fully covered by the Year 1 ending cash surplus plus Egypt July AR collections. No additional investor capital is required for these payments.

Sheet Annual P&L Summary Y1-Y5
A1: NORCO / Vestwoods Egypt — 5-Year Annual P&L Summary (USD)
A2: Period: August 2026 – July 2031 | Vestwoods: Egypt containers: Y1=6, Y2=7, Y3=9, Y4=11, Y5=15 | Sudan containers: Y1=4, Y2=5, Y3=6, Y4=8, Y5=10 | Algeria containers: Y1=3, Y2=4, Y3=6, Y4=7, Y5=8 | Libya containers: Y1=0, Y2=4, Y3=5, Y4=6, Y5=8 Al Reem Plastics: Egypt containers: Y1=10, Y2=20, Y3=30, Y4=30, Y5=40 | Sudan containers: Y1=5, Y2=10, Y3=20, Y4=25, Y5=30 | Nigeria containers: Y1=0, Y2=8, Y3=12, Y4=18, Y5=25
A4: DESCRIPTION | B4: Year 1 (Aug26-Jul27) | C4: Year 2 (Aug27-Jul28) | D4: Year 3 (Aug28-Jul29) | E4: Year 4 (Aug29-Jul30) | F4: Year 5 (Aug30-Jul31) | G4: 5-YEAR TOTAL
A5: REVENUE
A6: Egypt - Vestwoods Sales | B6: ='Monthly P&L Year 1'!N6 | C6: =B6*1.2 | D6: =C6*1.2 | E6: =D6*1.2 | F6: =E6*1.2 | G6: =SUM(B6:F6)
A7: Sudan - Vestwoods Sales | B7: ='Monthly P&L Year 1'!N7 | C7: =B7*1.2 | D7: =C7*1.2 | E7: =D7*1.2 | F7: =E7*1.2 | G7: =SUM(B7:F7)
A8: Algeria - Vestwoods Sales | B8: ='Monthly P&L Year 1'!N8 | C8: =B8*1.2 | D8: =C8*1.2 | E8: =D8*1.2 | F8: =E8*1.2 | G8: =SUM(B8:F8)
A9: Libya - Vestwoods Sales | B9: 0 | C9: 1576000 | D9: =C9*1.2 | E9: =D9*1.2 | F9: =E9*1.2 | G9: =SUM(B9:F9)
A10: Egypt - Al Reem Plastics Sales | B10: ='Monthly P&L Year 1'!N9 | C10: 1153766 | D10: 1730649 | E10: 1730649 | F10: 2307531 | G10: =SUM(B10:F10)
A11: Sudan - Al Reem Plastics Sales | B11: ='Monthly P&L Year 1'!N10 | C11: =52444*10 | D11: =52444*20 | E11: =52444*25 | F11: =52444*30 | G11: =SUM(B11:F11)
A12: Nigeria - Al Reem Plastics Sales | B12: 0 | C12: =52444*8 | D12: =52444*12 | E12: =52444*18 | F12: =52444*25 | G12: =SUM(B12:F12)
A13: TOTAL REVENUE | B13: =SUM(B6:B12) | C13: =SUM(C6:C12) | D13: =SUM(D6:D12) | E13: =SUM(E6:E12) | F13: =SUM(F6:F12) | G13: =SUM(G6:G12)
A14: YoY Revenue Growth | B14: — | C14: =(C13-B13)/B13 | D14: =(D13-C13)/C13 | E14: =(E13-D13)/D13 | F14: =(F13-E13)/E13
A15: COST OF GOODS SOLD
A16: COGS % of Revenue | B16: 0.6588 | C16: 0.6588 | D16: 0.6588 | E16: 0.6588 | F16: 0.6588
A17: TOTAL COGS | B17: 4081465.8 | C17: 6654914.3 | D17: 8573248.6 | E17: 10218798 | F17: 12532048 | G17: =SUM(B17:F17)
A18: GROSS PROFIT | B18: 2114147.2 | C18: 3446655.7 | D18: 4440182.8 | E18: 5292431.8 | F18: 6490490 | G18: =SUM(B18:F18)
A19: Gross Margin % | B19: 0.341 | C19: 0.341 | D19: 0.341 | E19: 0.341 | F19: 0.341 | G19: =G18/G13
A20: OPERATING EXPENSES
A21: Personnel Costs (staff plan + 4% VW / 3% Al Reem Egypt commissions) | B21: 513320.8 | C21: 660328.2 | D21: 840589.7 | E21: 1025095.7 | F21: 1368137.4 | G21: =SUM(B21:F21)
A22: Rent & Facilities | B22: 115200 | C22: 115200 | D22: 135000 | E22: 175000 | F22: 220000 | G22: =SUM(B22:F22)
A23: Marketing & Promotions | B23: 59600 | C23: 85000 | D23: 120000 | E23: 165000 | F23: 215000 | G23: =SUM(B23:F23)
A24: Operations, G&A, trade-finance interest & other | B24: 78400 | C24: 105000 | D24: 130000 | E24: 165000 | F24: 205000 | G24: =SUM(B24:F24)
A25: Depreciation & Amortisation | B25: 16800 | C25: 16800 | D25: 16800 | E25: 20000 | F25: 30000 | G25: =SUM(B25:F25)
A26: TOTAL OPERATING EXPENSES | B26: 783320.8 | C26: 982328.2 | D26: 1242389.7 | E26: 1550095.7 | F26: 2038137.4 | G26: =SUM(B26:F26)
A27: PROFITABILITY
A28: EBIT (Operating Profit) | B28: 1330826.4 | C28: 2464327.5 | D28: 3197793.1 | E28: 3742336.1 | F28: 4452352.6 | G28: =SUM(B28:F28)
A29: EBIT Margin % | B29: 0.215 | C29: 0.244 | D29: 0.246 | E29: 0.241 | F29: 0.234
A30: Corporate Income Tax (22.5%) | B30: 299435.9 | C30: 554473.7 | D30: 719503.4 | E30: 842025.6 | F30: 1001779.3 | G30: =SUM(B30:F30)
A31: NET PROFIT / (LOSS) | B31: 1031390.5 | C31: 1909853.8 | D31: 2478289.7 | E31: 2900310.5 | F31: 3450573.3 | G31: =SUM(B31:F31)
A32: Net Margin % | B32: 0.166 | C32: 0.189 | D32: 0.19 | E32: 0.187 | F32: 0.181
A33: Cumulative Net Profit | B33: 1031390.5 | C33: 2941244.3 | D33: 5419534 | E33: 8319844.5 | F33: 11770418 | G33: 11770418
A35: KEY INVESTMENT METRICS
A36: Total 5-Year Revenue | B36: USD 63.8M
A37: Total 5-Year Gross Profit | B37: USD 21.8M
A38: Total 5-Year Net Profit | B38: USD 11.8M
A39: Year 1 Net Profit | B39: USD 1,031,390 (16.6% net margin)
A40: Year 1 Required Investment (est.) | B40: USD 1,000,000 core (+ optional 500K accelerator, ceiling 1.5M)
A41: Vestwoods Credit Terms | B41: 10% deposit + 90% at 3-month credit after 6 months to 1 year of purchase
A42: Egypt Customer Payment Terms | B42: 30–60 days (accounts receivable)
A43: Sudan Payment Terms | B43: 50% upfront + 50% on delivery
A44: Libya Payment Terms | B44: 50% upfront + 50% on delivery
A45: Algeria Payment Terms | B45: 50% upfront + 50% on delivery or L/C
A46: Monthly Break-Even (Operations) | B46: Month 6 — January 2027
A47: Cumulative Break-Even | B47: Month 6 — January 2027
A48: 5-Year ROI on Investment | B48: 11.8
A49: Projected IRR (5-Year) | B49: 48% dividends-only · 79% incl. terminal value (50% stake, USD 1.0M)
A50: Staff at End of Year 5 | B50: 55 employees
A51: Egypt Containers (Year 1 / Year 5) | B51: Vestwoods: 6 containers / 15 containers. Al Reem Plastics: 10 containers / 40 containers
A52: Sudan Containers (Year 1 / Year 5) | B52: Vestwoods: 4 containers / 10 containers. Al Reem Plastics: 5 containers / 30 containers
A53: Algeria Containers (Year 1 / Year 5) | B53: Vestwoods: 3 containers / 8 containers
A54: Libya Containers (Year 2 / Year 5) | B54: Vestwoods: 4 containers / 8 containers
A55: Nigeria Containers (Year 2 / Year 5) | B55: Al Reem Plastics: 8 containers / 25 containers

Sheet 5Y Cash Flow
A1: Five-Year Cash Flow (USD)
A2: Y1 from the monthly sheet (100% prepayment). Y2+ under credit terms: 10% at PO + 90% at 3-month credit (~22.5% of Vestwoods supplier purchases outstanding at year end)
A4: ITEM | B4: Year 1 | C4: Year 2 | D4: Year 3 | E4: Year 4 | F4: Year 5
A5: Customer collections | B5: 5587787 | C5: 10449448 | D5: 12961442 | E5: 15448843 | F5: 18947673
A6: Investor capital (T1 + T2) | B6: 1000000 | C6: 0 | D6: 0 | E6: 0 | F6: 0
A7: Supplier payments — current-year purchases (net of year-end credit) | B7: -3738413 | C7: -5550945.9 | D7: -7248486.6 | E7: -8629084.1 | F7: -10624391
A8: Supplier payments — prior-year balances (Vestwoods credit + Al Reem payable) | B8: 0 | C8: -1138571 | D8: -1103968.4 | E8: -1324762 | F8: -1589714.4
A9: Operating expenses (cash; Y1 incl. USD 50,000 one-time setup) | B9: -827820.8 | C9: -965528.2 | D9: -1225589.7 | E9: -1530095.7 | F9: -2008137.4
A10: Corporate tax paid (prior year, in arrears) | B10: 0 | C10: -299435.9 | D10: -554473.7 | E10: -719503.4 | F10: -842025.6
A11: Dividends paid (100% of prior-year net profit) | B11: 0 | C11: -1031390.5 | D11: -1909853.8 | E11: -2478289.7 | F11: -2900310.5
A12: Capex | B12: 0 | C12: -25000 | D12: -30000 | E12: -35000 | F12: -40000
A13: NET ANNUAL CASH FLOW | B13: 2021553.2 | C13: 1438576.2 | D13: 889069.5 | E13: 732107.8 | F13: 943094.3
A14: CLOSING CASH POSITION | B14: 2021553.2 | C14: 3460129.4 | D14: 4349198.9 | E14: 5081306.7 | F14: 6024401
A16: MEMO — year-end balances
A17: Trade receivables (Vestwoods Egypt, 1 month + Y1 export balances) | B17: 607826 | C17: 259948.3 | D17: 311938 | E17: 374325.5 | F17: 449190.7
A18: Supplier balances payable next year (Vestwoods credit; Y1 also Al Reem) | B18: 1138571 | C18: 1103968.4 | D18: 1324762 | E18: 1589714.4 | F18: 1907657.3
A20: • STRENGTH — the Month-13 credit switch (10% down + 90% at 3-month credit) releases ~90% of Vestwoods container capital: Year-2 cash jumps despite full dividend payout.
A21: • STRENGTH — Al Reem's fast-turning houseware generates cash from the first quarter and smooths the battery cycle.
A22: • STRENGTH — closing cash rises every year while distributing 100% of profits and paying rising taxes; no capital call after Tranche 2.
A23: • RISK — Year 1 depends on the raise closing on time: peak self-funded deficit USD 903,954 (Jan-27); the USD 1.0M raise covers it with a USD 96K minimum cash position — the optional USD 0.5M accelerator lifts the buffer.

Sheet Market Detail
A1: Market Detail — Both Divisions
A2: Container allocations, revenue, margins, terms and market actions per year
A4: Market / Year | B4: Containers | C4: Revenue (USD) | D4: GM % | E4: Payment terms | F4: Key market action
A5: VESTWOODS — EGYPT
A6: Year 1 | B6: 6 | C6: 2599686 | D6: 0.21 | E6: Retail + 30–60 day dealer terms | F6: Two showrooms live; dealer network build; I LOCK wholesale anchor
A7: Year 2 | B7: 7 | C7: ='Annual P&L Summary Y1-Y5'!C6 | D7: 0.21 | E7: Retail + 30–60 day dealer terms | F7: Alexandria coverage via dealers; first C&I quotes
A8: Year 3 | B8: 9 | C8: ='Annual P&L Summary Y1-Y5'!D6 | D8: 0.21 | E8: Retail + 30–60 day dealer terms | F8: Alexandria branch opens; telecom accounts
A9: Year 4 | B9: 11 | C9: ='Annual P&L Summary Y1-Y5'!E6 | D9: 0.21 | E9: Retail + 30–60 day dealer terms | F9: B2G/tenders desk; C&I pipeline
A10: Year 5 | B10: 15 | C10: ='Annual P&L Summary Y1-Y5'!F6 | D10: 0.21 | E10: Retail + 30–60 day dealer terms | F10: 40+ dealer network; CKD assembly evaluation
A11: VESTWOODS — SUDAN
A12: Year 1 | B12: 4 | C12: ='Annual P&L Summary Y1-Y5'!B7 | D12: 0.131 | E12: 50% advance + 50% on delivery | F12: Committed buyer orders on arrival of first containers
A13: Year 2 | B13: 5 | C13: ='Annual P&L Summary Y1-Y5'!C7 | D13: 0.131 | E13: 50% advance + 50% on delivery | F13: 3 dealers; add Omdurman, El Obeid
A14: Year 3 | B14: 6 | C14: ='Annual P&L Summary Y1-Y5'!D7 | D14: 0.131 | E14: 50% advance + 50% on delivery | F14: Telecom tower contracts
A15: Year 4 | B15: 8 | C15: ='Annual P&L Summary Y1-Y5'!E7 | D15: 0.131 | E15: 50% advance + 50% on delivery | F15: C&I projects; Khartoum tenders
A16: Year 5 | B16: 10 | C16: ='Annual P&L Summary Y1-Y5'!F7 | D16: 0.131 | E16: 50% advance + 50% on delivery | F16: Standalone Sudan office consideration
A17: VESTWOODS — ALGERIA
A18: Year 1 | B18: 3 | C18: ='Annual P&L Summary Y1-Y5'!B8 | D18: 0.131 | E18: 100% LC before shipment | F18: First LC orders under negotiated agency (FOB Jebel Ali)
A19: Year 2 | B19: 4 | C19: ='Annual P&L Summary Y1-Y5'!C8 | D19: 0.131 | E19: 100% LC before shipment | F19: Agency formalised; dealer sub-network
A20: Year 3 | B20: 6 | C20: ='Annual P&L Summary Y1-Y5'!D8 | D20: 0.131 | E20: 100% LC before shipment | F20: Solar programme alignment
A21: Year 4 | B21: 7 | C21: ='Annual P&L Summary Y1-Y5'!E8 | D21: 0.131 | E21: 100% LC before shipment | F21: C&I entries; coverage expansion
A22: Year 5 | B22: 8 | C22: ='Annual P&L Summary Y1-Y5'!F8 | D22: 0.131 | E22: 100% LC before shipment | F22: Scale; assess in-country JV
A23: VESTWOODS — LIBYA
A24: Year 1 | B24: — | C24: 0 | D24: 0 | E24: Advance / confirmed LC | F24: —
A25: Year 2 | B25: 4 | C25: ='Annual P&L Summary Y1-Y5'!C9 | D25: 0.131 | E25: Advance / confirmed LC | F25: Sign Tripoli + Benghazi distributors
A26: Year 3 | B26: 5 | C26: ='Annual P&L Summary Y1-Y5'!D9 | D26: 0.131 | E26: Advance / confirmed LC | F26: Residential solar in outage districts
A27: Year 4 | B27: 6 | C27: ='Annual P&L Summary Y1-Y5'!E9 | D27: 0.131 | E27: Advance / confirmed LC | F27: C&I backup; NGO/health supply
A28: Year 5 | B28: 8 | C28: ='Annual P&L Summary Y1-Y5'!F9 | D28: 0.131 | E28: Advance / confirmed LC | F28: Secondary-city coverage
A29: AL REEM PLASTICS — EGYPT
A30: Year 1 | B30: 10 | C30: ='Annual P&L Summary Y1-Y5'!B10 | D30: 0.253 | E30: Retail + wholesale 30–45 days | F30: Launch through both showrooms + wholesale to retailers
A31: Year 2 | B31: 20 | C31: ='Annual P&L Summary Y1-Y5'!C10 | D31: 0.253 | E31: Retail + wholesale 30–45 days | F31: Hypermarket listings (Carrefour-class)
A32: Year 3 | B32: 30 | C32: ='Annual P&L Summary Y1-Y5'!D10 | D32: 0.253 | E32: Retail + wholesale 30–45 days | F32: Online channel + Alexandria dealers
A33: Year 4 | B33: 30 | C33: ='Annual P&L Summary Y1-Y5'!E10 | D33: 0.253 | E33: Retail + wholesale 30–45 days | F33: Private-label conversations
A34: Year 5 | B34: 40 | C34: ='Annual P&L Summary Y1-Y5'!F10 | D34: 0.253 | E34: Retail + wholesale 30–45 days | F34: Nationwide wholesale coverage
A35: AL REEM PLASTICS — SUDAN
A36: Year 1 | B36: 5 | C36: ='Annual P&L Summary Y1-Y5'!B11 | D36: 0.2 | E36: 50% advance + 50% on delivery | F36: Same sub-distributor channel as Vestwoods
A37: Year 2 | B37: 10 | C37: ='Annual P&L Summary Y1-Y5'!C11 | D37: 0.2 | E37: 50% advance + 50% on delivery | F37: Khartoum + Port Sudan dealers
A38: Year 3 | B38: 20 | C38: ='Annual P&L Summary Y1-Y5'!D11 | D38: 0.2 | E38: 50% advance + 50% on delivery | F38: Range extension to 100+ SKUs
A39: Year 4 | B39: 25 | C39: ='Annual P&L Summary Y1-Y5'!E11 | D39: 0.2 | E39: 50% advance + 50% on delivery | F39: Second distributor
A40: Year 5 | B40: 30 | C40: ='Annual P&L Summary Y1-Y5'!F11 | D40: 0.2 | E40: 50% advance + 50% on delivery | F40: Scale with market recovery
A41: AL REEM PLASTICS — Nigeria
A42: Year 1 | B42: 0 | C42: 0 | D42: 0.2 | E42: 50% advance + 50% on delivery
A43: Year 2 | B43: 8 | C43: ='Annual P&L Summary Y1-Y5'!C12 | D43: 0.2 | E43: 50% advance + 50% on delivery
A44: Year 3 | B44: 12 | C44: ='Annual P&L Summary Y1-Y5'!D12 | D44: 0.2 | E44: 50% advance + 50% on delivery
A45: Year 4 | B45: 18 | C45: ='Annual P&L Summary Y1-Y5'!E12 | D45: 0.2 | E45: 50% advance + 50% on delivery
A46: Year 5 | B46: 25 | C46: ='Annual P&L Summary Y1-Y5'!F12 | D46: 0.2 | E46: 50% advance + 50% on delivery
A47: Sudan cash terms mean revenue is collected before or at shipment; Algeria LC-before-shipment carries zero receivable risk.

Sheet Funding & Returns
A1: Funding Structure & Investor Returns
A2: USD 1,000,000 core for 50% of NORCO Egypt (T1 500K at close + T2 500K at Month 4) | optional 500K accelerator, ceiling USD 1.5M | dividends 100% payout in arrears | terminal at 5× Year-5 net profit
A4: A. TRANCHE STRUCTURE
A5: Tranche | B5: Amount (USD) | C5: Timing | D5: Gate / purpose
A6: Tranche 1 — Launch | B6: 500000 | C6: Month 1 (Aug-26, at close) | D6: First Vestwoods containers (Sinosure credit), first Al Reem containers, setup, opex runway
A7: Tranche 2 — Scale | B7: 500000 | C7: Month 4 (Nov-26), milestone-gated | D7: Released on ≥3 containers sold through + Sudan advances received; funds container waves 4–13
A8: Optional accelerator | B8: 500000 | C8: Months 6–12, by mutual agreement | D8: Buffer / faster Al Reem & Libya ramp; brings total to the USD 1.5M ceiling
A9: Core total (T1+T2) | B9: =SUM(B6:B7)
A11: B. SIZING
A12: USD 1,000,000 core (as modelled) | B12: Covers the USD 903,954 peak self-funded deficit (Jan-27) with a USD 96,046 minimum cash position; Year-1 ending cash USD 2,021,553
A13: USD 1,500,000 with accelerator | B13: Adds ~USD 500K standing buffer and pulls Al Reem and Libya volumes forward
A15: C. INVESTOR CASH FLOW — 50% equity of NORCO Egypt for USD 1.0M
A16: Flow (USD) | B16: Y0 (close) | C16: Year 1 | D16: Year 2 | E16: Year 3 | F16: Year 4 | G16: Year 5
A17: Capital invested | B17: -1000000 | C17: 0 | D17: 0 | E17: 0 | F17: 0 | G17: 0
A18: Dividends (50% of prior-year net profit) | B18: 0 | C18: 0 | D18: 515695.2 | E18: 954926.9 | F18: 1239144.9 | G18: 1450155.2
A19: Terminal value (50% × 5 × Y5 net profit) | B19: 0 | C19: 0 | D19: 0 | E19: 0 | F19: 0 | G19: 8626433.2
A20: Net investor cash flow | B20: =SUM(B17:B19) | C20: =SUM(C17:C19) | D20: =SUM(D17:D19) | E20: =SUM(E17:E19) | F20: =SUM(F17:F19) | G20: =SUM(G17:G19)
A21: IRR — incl. terminal value | B21: =IRR(B20:G20) | D21: MOIC | E21: =SUM(C20:G20)/-B20
A22: IRR — dividends only (excl. terminal) | B22: 0.47675903 | D22: MOIC | E22: 4.1599222
A24: D. INVESTOR PROTECTIONS
A25: • Tranche 2 released only against verified Month-4 milestones (≥3 containers sold through + Sudan advances received).
A26: • Quarterly management accounts; monthly cash & inventory reporting across both divisions; USD-denominated books.
A27: • Egypt customers on max 60-day terms; Sudan cash-before-shipment; Algeria LC only; Libya advance/LC.
A28: • Exclusive Vestwoods agency and the Al Reem (Angola) affiliated supply agreement held within the group; assignable as security.
A29: • Founder pre-investment of USD 14,517 already deployed; board seat and reserved matters for the investor.

Sheet Shareholding
A1: Shareholding — NORCO Egypt (the investment vehicle)
A2: Investor subscribes into the Egypt operating company; NORCO UAE anchors supply relationships as a 20% shareholder
A4: Shareholder | B4: NORCO Egypt % | C4: Notes
A5: Investor (USD 1.0M capital) | B5: 0.5 | C5: Cash for 50% of NORCO Egypt; board seat; reserved matters
A6: NORCO General Trading L.L.C. (UAE) | B6: 0.2 | C6: Holds the Vestwoods exclusive agency & Al Reem (Angola) supply relationship
A7: Fadi Jannan — Chairman & Founder | B7: 0.2 | C7: Executive lead; combined founder-side interest 40% (20% direct + 20% via NORCO UAE)
A8: Partner A | B8: 0.05 | C8: Existing partner
A9: Partner B | B9: 0.05 | C9: Existing partner
A10: TOTAL | B10: =SUM(B4:B8)
A12: • Founder-side combined interest = 40%: 20% held directly by the Chairman + 20% held via NORCO General Trading L.L.C. (UAE), which he controls (80%).
A13: • NORCO UAE contributes the exclusive Vestwoods agency and the Al Reem (Angola) supply relationship to the Egypt company under long-term agreements.
A14: • Dividend policy: 100% of net profit distributed annually in arrears — investor receives 50% of every distribution.

Sheet Dashboard
A1: Investor Dashboard
A2: Headline metrics — NORCO Egypt, both divisions
A4: Total 5-year revenue (USD) | B4: 63844383
A5: Total 5-year gross profit (USD) | B5: 21783908
A6: Total 5-year net profit (USD) | B6: 11770418
A7: Year 1 revenue (USD) | B7: 6195613
A8: Year 1 net profit (USD) | B8: 1031390.5
A9: Year 5 net profit (USD) | B9: 3450573.3
A10: Operating break-even | B10: Month 6 (Jan-27)
A11: Cumulative break-even | B11: Month 6 (Jan-27)
A12: Peak self-funded cash deficit (USD) | B12: 903954
A13: Year-1 ending cash with raise (USD) | B13: 2021553.2
A14: Year-5 closing cash (USD) | B14: 6024401
A15: Investment (USD, for 50% of NORCO Egypt) | B15: 1000000
A16: Investor IRR (dividends + terminal) | B16: 0.78844899
A17: Investor MOIC | B17: 12.786355
A18: Founder pre-operational investment (USD) | B18: 14517
A20: Chart data (USD)
A21: Year | B21: Y1 | C21: Y2 | D21: Y3 | E21: Y4 | F21: Y5
A22: Vestwoods revenue | B22: 5356510 | C22: 8003812 | D22: 9604574.4 | E22: 11525489 | F22: 13830587
A23: Al Reem revenue | B23: 839103 | C23: 2097758 | D23: 3408857 | E23: 3985741 | F23: 5191951
A24: Net profit | B24: 1031390.5 | C24: 1909853.8 | D24: 2478289.7 | E24: 2900310.5 | F24: 3450573.3
